topsis_chirag_102303003/__init__.py
topsis_chirag_102303003/cli.py
topsis_chirag_102303003/topsis.py
topsis_chirag_102303003-1.0.0.dist-info/LICENSE
topsis_chirag_102303003-1.0.0.dist-info/METADATA
topsis_chirag_102303003-1.0.0.dist-info/WHEEL
topsis_chirag_102303003-1.0.0.dist-info/entry_points.txt
topsis_chirag_102303003-1.0.0.dist-info/top_level.txt
topsis_chirag_102303003-1.0.0.dist-info/RECORD
