Metadata-Version: 2.2
Name: Topsis-Chirag-102303003
Version: 1.0.0
Summary: TOPSIS implementation command line package
Author-email: Chirag Gupta <cgupta3_be23@thapar.edu>
Classifier: Programming Language :: Python :: 3
Classifier: License :: OSI Approved :: MIT License
Classifier: Operating System :: OS Independent
Requires-Python: >=3.8
License-File: LICENSE
Requires-Dist: pandas
Requires-Dist: numpy
